[
	{
		"id": "2f",
		"label": "2F",
		"description": "入口",
		"items": [
			{
				"id": "entrance",
				"name": "入口",
				"description": "註記: 報到處在四樓哦！",
				"meshes": ["floor__outside__front_door_desolver", "floor__outside__front_2f_glass"]
			},
			{
				"id": "stairs_2f",
				"name": "樓梯",
				"description": "往3F",
				"meshes": ["floor__2f__stairs_2f_r", "floor__2f__stairs_2f_l"]
			}
		]
	},
	{
		"id": "3f",
		"label": "3F",
		"description": "服務台、議程廳 R0~R3、攤位",
		"items": [
			{
				"id": "service_table",
				"name": "服務台",
				"description": "在這裡尋找工作人員協助！",
				"meshes": ["floor__3f__service_table_table", "floor__3f__service_table_text"]
			},
			{
				"id": "badge_sign",
				"name": "識別證簽名處",
				"description": "領到識別證後可以在這簽名！",
				"meshes": ["floor__3f__badge_sign_table", "floor__3f__badge_sign_text", "floor__3f__badge_sign_table001", "floor__3f__badge_sign_text001"]
			},
			{
				"id": "r0",
				"name": "R0",
				"description": "議程廳",
				"meshes": ["floor__3f__room_r0_3f", "floor__3f__room_r0_slope", "floor__3f__room_r0_arrow_1", "floor__3f__room_r0_arrow_2"]
			},
			{
				"id": "r1",
				"name": "R1",
				"description": "議程廳",
				"meshes": ["floor__3f__room_r1", "floor__3f__room_r1_arrow_1", "floor__3f__room_r1_arrow_2"]
			},
			{
				"id": "r2",
				"name": "R2",
				"description": "議程廳",
				"meshes": ["floor__3f__room_r2", "floor__3f__room_r2_arrow_1", "floor__3f__room_r2_arrow_2"]
			},
			{
				"id": "r3",
				"name": "R3",
				"description": "議程廳",
				"meshes": ["floor__3f__room_r3", "floor__3f__room_r3_arrow_1", "floor__3f__room_r3_arrow_2"]
			},
			{
				"id": "amd",
				"name": "AMD",
				"description": "贊助商攤位",
				"longDescription": "AMD 推動高效能運算、繪圖及視覺技術。全球消費者、世界 500 強企業及研究機構透過 AMD 來改善生活、工作及娛樂。AMD 致力研發領先的高效能產品，不斷突破極限。",
				"link": "https://www.amd.com/zh-tw.html",
				"meshes": ["floor__3f__amd_table", "floor__3f__amd_text"]
			},
			{
				"id": "twinkleai",
				"name": "Twinkle AI",
				"description": "社群攤位",
				"longDescription": "Twinkle AI 成立於 2024 年底，是一個專注於繁體中文語言模型的開源研究社群。從 LLaMA 模型起步，持續建構專為繁體中文量身打造的實用技術，致力於打造最貼近繁體中文應用需求的大型語言模型。",
				"link": "https://twinkleai.tw/",
				"meshes": ["floor__3f__twinkleai_table", "floor__3f__twinkleai_text"]
			},
			{
				"id": "sitcon_3f",
				"name": "SITCON 學生計算機年會",
				"description": "主辦單位攤位",
				"longDescription": "學生計算機年會（SITCON）自 2012 年發起，以學生為本、由學生自發舉辦，長期投身學生資訊教育與推廣開源精神。是東亞最大的學生資訊社群與研討會，希望引領更多學子踏入資訊的殿堂。",
				"link": "https://sitcon.org",
				"meshes": ["floor__3f__sitcon_table", "floor__3f__sitcon_text"]
			},
			{
				"id": "ruby",
				"name": "Ruby Taiwan",
				"description": "社群攤位",
				"longDescription": "Ruby Taiwan 成立於 2008 年，主要針對 Ruby 程式語言及軟體開發，進行業界的交流及分享，提昇開發人員的技術深度與廣度。",
				"link": "https://www.instagram.com/rubytaiwan2008/",
				"meshes": ["floor__3f__ruby_table", "floor__3f__ruby_text"]
			},
			{
				"id": "tdna",
				"name": "TDNA 台灣數位遊牧者協會",
				"description": "社群攤位",
				"longDescription": "TDNA 致力於推動台灣成為亞洲重要的數位遊牧與遠距工作樞紐，串聯政府、地方城市、產業夥伴與國際社群，協助政策推動、示範場域建置與跨國交流，並定期舉辦國際論壇與社群聚會。",
				"link": "https://dna.org.tw",
				"meshes": ["floor__3f__tdna_table", "floor__3f__tdna_text"]
			},
			{
				"id": "aia",
				"name": "AIA 台灣人工智慧學校",
				"description": "贊助商攤位",
				"longDescription": "台灣人工智慧學校深耕 8 年，培訓 1.3 萬名 AI 人才、服務逾千家企業。近年推動 AI 認證與產業人才指引，並發起「公民 AI 素養計畫」落實普惠 AI。",
				"link": "https://aiacademy.tw/",
				"meshes": ["floor__3f__aia_table", "floor__3f__aia_text"]
			},
			{
				"id": "schools_1",
				"name": "學生社群 (SCINT/SCAICT/SCIST)",
				"description": "社群攤位",
				"longDescription": "北臺灣學生資訊社群 SCINT、中部高中電資社團聯合會議 SCAICT、南臺灣學生資訊社群 SCIST，三大學生資訊社群攜手合作，致力於在北、中、南部推廣程式、資安、專案開發等資訊教育，扶植各地高中職生資訊社群的發展。",
				"meshes": ["floor__3f__schools_1_table", "floor__3f__schools_1_text", "floor__3f__schools_2_table"]
			}
		]
	},
	{
		"id": "4f",
		"label": "4F",
		"description": "報到、攤位、午餐、交誼廳",
		"items": [
			{
				"id": "register",
				"name": "報到處",
				"description": "在這裡報到！",
				"meshes": ["floor__4f__register_left_table", "floor__4f__register_left_text", "floor__4f__register_right_table", "floor__4f__register_right_text"]
			},
			{
				"id": "s0",
				"name": "S0 交誼廳",
				"description": "交流空間",
				"meshes": ["floor__4f__room_s"]
			},
			{
				"id": "lunch",
				"name": "午餐區",
				"description": "用餐空間",
				"meshes": [
					"floor__4f__dining_table_left",
					"floor__4f__dining_table_left001",
					"floor__4f__dining_table_left002",
					"floor__4f__dining_table_left003",
					"floor__4f__dining_table_left004",
					"floor__4f__dining_table_left005",
					"floor__4f__dining_table_left006",
					"floor__4f__dining_table_left007",
					"floor__4f__dining_table_left008",
					"floor__4f__dining_table_left009",
					"floor__4f__dining_table_left010",
					"floor__4f__dining_table_left011",
					"floor__4f__dining_table_left012",
					"floor__4f__dining_table_left013",
					"floor__4f__dining_table_left014",
					"floor__4f__dining_table_left015",
					"floor__4f__dining_table_left016",
					"floor__4f__dining_table_left017",
					"floor__4f__dining_table_left018",
					"floor__4f__dining_table_left019",
					"floor__4f__dining_table_left020",
					"floor__4f__dining_table_left021",
					"floor__4f__dining_table_left022",
					"floor__4f__dining_table_left023",
					"floor__4f__dining_table_left024",
					"floor__4f__dining_table_left025",
					"floor__4f__dining_table_left026",
					"floor__4f__dining_table_left027",
					"floor__4f__dining_table_left028",
					"floor__4f__dining_table_left029",
					"floor__4f__dining_table_left030",
					"floor__4f__dining_table_left031",
					"floor__4f__dining_table_left032",
					"floor__4f__dining_table_left033",
					"floor__4f__dining_table_left034",
					"floor__4f__dining_table_left035",
					"floor__4f__dining_table_left036",
					"floor__4f__dining_table_left037",
					"floor__4f__dining_table_left038",
					"floor__4f__dining_table_left039",
					"floor__4f__dining_table_left040",
					"floor__4f__dining_table_left041",
					"floor__4f__dining_table_right",
					"floor__4f__dining_table_right001",
					"floor__4f__dining_table_right002",
					"floor__4f__dining_table_right003",
					"floor__4f__dining_table_right004",
					"floor__4f__dining_table_right005",
					"floor__4f__dining_table_right006",
					"floor__4f__dining_table_right007",
					"floor__4f__dining_table_right008",
					"floor__4f__dining_table_right009",
					"floor__4f__dining_table_right010",
					"floor__4f__dining_table_right011",
					"floor__4f__dining_table_right012",
					"floor__4f__dining_table_right013",
					"floor__4f__dining_table_right014",
					"floor__4f__dining_table_right015",
					"floor__4f__dining_table_right016",
					"floor__4f__dining_table_right017",
					"floor__4f__dining_table_right018",
					"floor__4f__dining_table_right019",
					"floor__4f__dining_table_right020",
					"floor__4f__dining_table_right021",
					"floor__4f__dining_table_right022",
					"floor__4f__dining_table_right023",
					"floor__4f__dining_table_right024",
					"floor__4f__dining_table_right025",
					"floor__4f__dining_table_right026",
					"floor__4f__dining_table_right027",
					"floor__4f__dining_table_right028",
					"floor__4f__dining_table_right029",
					"floor__4f__dining_table_right030",
					"floor__4f__dining_table_right031",
					"floor__4f__dining_table_right032",
					"floor__4f__dining_table_right033",
					"floor__4f__dining_table_right034",
					"floor__4f__dining_table_right035",
					"floor__4f__dining_table_right036",
					"floor__4f__dining_table_right037",
					"floor__4f__dining_table_right038",
					"floor__4f__dining_table_right039",
					"floor__4f__dining_table_right040",
					"floor__4f__dining_table_right041"
				]
			},
			{
				"id": "poster",
				"name": "海報展",
				"description": "海報展示區",
				"meshes": ["floor__4f__poster_table", "floor__4f__poster_text"]
			},
			{
				"id": "sitcon_shop",
				"name": "SITCON 紀念品販賣",
				"description": "快來這裡買酷酷的 SITCON 紀念品！",
				"meshes": ["floor__4f__sitcon_shop_table", "floor__4f__sitcon_shop_text"]
			},
			{
				"id": "line",
				"name": "LINE台灣",
				"description": "贊助商攤位",
				"longDescription": "總部位於日本的 LINE 以「拉近你我的距離」為企業使命，透過多元的行動服務與內容，致力將人們、資訊與社會緊密連結。積極實現「智慧入口」的願景，持續提供用戶享有最即時、便利的行動生活。",
				"link": "https://techblog.lycorp.co.jp/zh-hant/line-tech-fresh-2026-summer",
				"meshes": ["floor__4f__line_table", "floor__4f__line_text"]
			},
			{
				"id": "tsmc",
				"name": "台積電",
				"description": "贊助商攤位",
				"longDescription": "台積電是全球領先的晶圓製造服務公司，其 IT 以 AI 驅動及雲端原生服務，支援半導體前瞻製程，實現「FAB RUNS ON CODE」。現在加入 IT 實習，展開你的數位卓越之旅！",
				"link": "https://www.tsmc.com/chinese",
				"meshes": ["floor__4f__tsmc_table", "floor__4f__tsmc_text"]
			},
			{
				"id": "teamt5",
				"name": "TeamT5 杜浦數位安全",
				"description": "贊助商攤位",
				"longDescription": "TeamT5 專注威脅情資與 EDR 研究，具 20 年 APT 與惡意程式分析經驗，並投入人才培育，每年辦理資安培訓營，且提供實習與學生社群支持。",
				"link": "https://teamt5.org/",
				"meshes": ["floor__4f__teamt5_table", "floor__4f__teamt5_text"]
			},
			{
				"id": "zuso",
				"name": "ZUSO Generation 如梭世代",
				"description": "贊助商攤位",
				"longDescription": "ZUSO 如梭世代成立於 2019 年，是深耕臺灣的專業資安服務業者，專注於紅隊演練、滲透測試與資安顧問服務，協助企業驗證資安防護能力，並持續深耕臺灣資安人才培育。",
				"link": "https://zuso.ai",
				"meshes": ["floor__4f__zuso_table", "floor__4f__zuso_text"]
			},
			{
				"id": "sjmlanguage",
				"name": "尚進美日韓語",
				"description": "贊助商攤位",
				"longDescription": "尚進美日韓語專注真人線上一對一外語教學，幫助學生提升英文實力，從考試到實習面試，打造未來職場必備的國際溝通能力。",
				"link": "https://scedu.com.tw/",
				"meshes": ["floor__4f__sjmlanguage_table", "floor__4f__sjmlanguage_text"]
			},
			{
				"id": "moztw",
				"name": "MozTW 社群 / 摩茲工寮",
				"description": "社群攤位",
				"longDescription": "MozTW 是台灣 Mozilla 愛好者的實體社群，負責維護 Mozilla 大部分軟體的正體中文版本與語言套件的在地化。摩茲工寮是 MozTW 為開放社群與活動所設計、由社群共同管理的空間。",
				"link": "https://moztw.org",
				"meshes": ["floor__4f__moztw_table", "floor__4f__moztw_text"]
			},
			{
				"id": "g0v",
				"name": "g0v 零時政府",
				"description": "社群攤位",
				"longDescription": "g0v 是發源於台灣的公民科技社群，藉由提供更容易閱讀的資訊、更容易使用的數位服務，推進公民參與公共議題。g0v Summit 則是為了與台灣及世界各地公民駭客互相連結所舉辦的雙年會。",
				"link": "https://summit.g0v.tw/2026/",
				"meshes": ["floor__4f__g0v_table", "floor__4f__g0v_text"]
			},
			{
				"id": "coscup",
				"name": "COSCUP",
				"description": "社群攤位",
				"longDescription": "COSCUP（開源人年會）是由一群自由與開放原始碼軟體愛好者發起，致力於推廣開放原始碼精神與技術，專為開放原始碼的開發者（Coders）、使用者（Users）和推廣者（Promoters）舉辦的年度研討會。",
				"link": "https://coscup.org",
				"meshes": ["floor__4f__coscup_table", "floor__4f__coscup_text"]
			},
			{
				"id": "ocf",
				"name": "OCF 開放文化基金會",
				"description": "社群攤位",
				"longDescription": "開放文化基金會（OCF）是一個非營利性的組織，透過推廣開放科技和跨界合作，在臺灣持續的銜繫科技社群與其他公／私領域，促成開放共創保障數位人權、支持透明涵融的數位公民社會。",
				"link": "https://ocf.tw/",
				"meshes": ["floor__4f__ocf_table", "floor__4f__ocf_text"]
			},
			{
				"id": "jsdc",
				"name": "JSDC",
				"description": "社群攤位",
				"longDescription": "JavaScript 開發者年會（JSDC）是台灣最大的 JavaScript 年度性技術研討會，旨在提供台灣中高階 JavaScript 技術人才與世界最新 JavaScript 相關技術討論與分享，整合來自獨立開發者、企業、組織及機構的科技力量。",
				"link": "https://www.facebook.com/JSDC.TW",
				"meshes": ["floor__4f__jsdc_table", "floor__4f__jsdc_text"]
			},
			{
				"id": "wordpress",
				"name": "WordPress 台灣社群",
				"description": "社群攤位",
				"longDescription": "WordPress 台灣社群聚集熱愛網站開發、設計及內容創作的愛好者與專業人士，透過舉辦 WordPress Meetup、工作坊及年會 WordCamp，分享最新技術、交流經驗，並建立緊密的合作網絡。",
				"link": "https://www.facebook.com/groups/wordpresstw",
				"meshes": ["floor__4f__wordpress_table", "floor__4f__wordpress_text"]
			},
			{
				"id": "tkug",
				"name": "Taiwan Kotlin User Group",
				"description": "社群攤位",
				"longDescription": "Taiwan Kotlin User Group 是一個讓大家可以討論與交流 Kotlin 程式語言各種使用經驗，舉辦相關活動的社群。如果對 Kotlin 有興趣，想要多瞭解一些，歡迎來社群一起聚會！",
				"link": "https://www.facebook.com/kotlintwn",
				"meshes": ["floor__4f__tkug_table", "floor__4f__tkug_text"]
			},
			{
				"id": "lzgh",
				"name": "綠洲計畫 LZGH",
				"description": "社群攤位",
				"longDescription": "綠洲計畫透過建立社群平臺的交流分享及實體活動舉辦，幫助尋求特殊選才管道入學的學生，以及在體制或非體制內不易獲取資源的弱勢學生，讓他們能得到更多有利學習的條件，自我肯定與突破。",
				"link": "https://lzgh.org/",
				"meshes": ["floor__4f__lzgh_table", "floor__4f__lzgh_text"]
			},
			{
				"id": "ubuntutw",
				"name": "Ubuntu 台灣社群",
				"description": "社群攤位",
				"longDescription": "Ubuntu-TW 成立於 2005 年 6 月，是由數名愛好者發起、以推廣 Ubuntu 為目標的台灣在地社群。定期舉辦 Release Party，並在各大開源社群擺攤展示，歡迎各路新手高手加入！",
				"link": "https://www.facebook.com/ubuntu.tw",
				"meshes": ["floor__4f__ubuntutw_table", "floor__4f__ubuntutw_text"]
			},
			{
				"id": "cntug",
				"name": "Cloud Native Taiwan User Group",
				"description": "社群攤位",
				"longDescription": "Cloud Native Taiwan User Group（CNTUG）是一個致力於推廣 Cloud Native 雲端原生相關技術的臺灣在地化社群，提供技術交流平台，聚集各行各業的使用者、開發者和傳教者，推動臺灣在雲端原生領域的發展。",
				"link": "https://fb.cloudnative.tw",
				"meshes": ["floor__4f__cntug_table", "floor__4f__cntug_text"]
			},
			{
				"id": "zdc",
				"name": "ZeroDay C00kie 零日餅乾社",
				"description": "社群攤位",
				"longDescription": "ZeroDay C00kie 社團課程涵蓋網頁安全、數位鑑識以及資安相關證照培訓等主題，本年度規劃讀書會與 Crypto 密碼學系列課程，透過循序漸進的課程安排與互動式討論，協助社員從基礎到進階逐步提升。",
				"link": "https://www.instagram.com/zeroday_cookie",
				"meshes": ["floor__4f__zdc_table", "floor__4f__zdc_text"]
			}
		]
	}
]
